sqlquerypp/__init__.py
sqlquerypp/compiler.py
sqlquerypp/sqlquerypp.cpython-313-x86_64-linux-musl.so
sqlquerypp/sqlquerypp.pyi
sqlquerypp/types.py
sqlquerypp.libs/libgcc_s-0cd532bd.so.1
sqlquerypp-0.1.0a5.dist-info/METADATA
sqlquerypp-0.1.0a5.dist-info/WHEEL
sqlquerypp-0.1.0a5.dist-info/RECORD
sqlquerypp-0.1.0a5.dist-info/licenses/LICENSE
sqlquerypp-0.1.0a5.dist-info/sboms/auditwheel.cdx.json
