Metadata-Version: 2.4
Name: sqlquerypp
Version: 0.1.0a5
Classifier: Development Status :: 3 - Alpha
Classifier: Intended Audience :: Developers
Classifier: License :: OSI Approved :: MIT License
Classifier: Operating System :: MacOS
Classifier: Operating System :: Microsoft :: Windows
Classifier: Operating System :: POSIX :: Linux
Classifier: Programming Language :: Python :: 3
Classifier: Programming Language :: Python :: 3.9
Classifier: Programming Language :: Python :: 3.10
Classifier: Programming Language :: Python :: 3.11
Classifier: Programming Language :: Python :: 3.12
Classifier: Programming Language :: Python :: 3.13
Classifier: Programming Language :: Python :: Implementation :: CPython
Classifier: Programming Language :: Python
Classifier: Programming Language :: Rust
Classifier: Typing :: Typed
License-File: LICENSE
Summary: SQL query preprocessor for generating optimized queries
Requires-Python: >=3.9
Project-URL: source, https://github.com/puzzleYOU/sqlquerypp
